[{"id":0,"alias":"iShares Global Clean Energy","epic":"KA.D.INRG.DAILY.IP","data":{"firstClose":1014.75,"beforeRangeFirstClose":1054.5,"firstDiff":"1.33","lastTime":"2021-11-26 15:00:00","lastOpen":1015.75,"lastClose":1009.75,"lastCloseAsk":1013,"lastCloseBid":1006.5,"lastHigh":1016.25,"lastLow":1006.5,"lastDiff":"0.84","nolastPriceVolatile":true,"lineData":{"support":1001.25,"resistance":1001.25,"midrange":1001.25,"momentumLimitBuyLine":1007.13,"momentumLimitSellLine":995.37,"tradeLimitBuyLine":1018.89,"tradeLimitSellLine":983.61},"lineDistance":0,"previousTrend":"ranging","trend4Hours":"bearish","trend4HoursDiff":40.25,"trend4HoursDiffPerc":50.79,"first4HoursClose":1050,"last4HoursClose":1009.75,"highest4HourPrice":1080.5,"lowest4HourPrice":1001.25,"priceDiff4Hours":79.25,"is4HoursTrendOveride":false,"is4HoursNotRanging":true,"trend":"ranging","trendDiff":5,"trendDiffPerc":"50% (0.50)","beforeRangeTrend":"bearish","beforeRangeFirstCloseData":{"price":1045.75,"open":1045.75,"close":1054.5,"high":1057,"low":1045,"diff":9,"time":"2021-11-22 14:00:00","closeAsk":1058.6,"closeBid":1050.4},"beforeRangeTrendDiff":44.75,"beforeRangeTrendDiffPerc":4.43,"rangedata_indexes":[0,1,2,3,4,5,6,7,18,19,20,21,22,23],"lastRangeData":{"price":1009.75,"open":1015.75,"close":1009.75,"high":1016.25,"low":1006.5,"diff":6,"time":"2021-11-26 15:00:00","closeAsk":1013,"closeBid":1006.5},"recentrange":[18,19,20,21,22,23],"rangeConfirmations":14,"recentTrendArr":[{"movement":"up","open":1008.5,"close":1011.5},{"movement":"up","open":1011.5,"close":1011.5},{"movement":"down","open":1012,"close":1011.25},{"movement":"down","open":1015.75,"close":1009.75}],"recentTrend":"ranging","recentUps":2,"recentDowns":2,"recentMovementValue":-1.75,"recentMovementValueDiffPerc":"0.03%","isRangeAreaGood":false,"isRangeConfirmationsGreaterThanLimit":true,"isRecentRangeOverLimit":true,"recentRangeIndex21":3,"recentRangeIndex22":4,"recentRangeIndex23":5,"updatedtrend":"bearish","islastCloseAboveBelowLines":true,"isRecentTrendPivoting":true,"isRecentTrendSameAsTrend":false,"isBeforeRangeSameAsTrend":true,"isBeforeRangeTrendNotBroken":true,"isBeforeRangeSameAs4HourTrend":true,"isRecentTrendSameAs4HourTrend":false,"isBreakingThroughRange":true,"isWithinTradeThreshold":true,"isNoVolatileGap":true,"volatilityGapAnalysis":[],"totalMissingHours":62,"noBumpInRange":false,"bumps":[{"idx":8,"close":1023.75},{"idx":9,"close":1033.25},{"idx":10,"close":1033},{"idx":11,"close":1034.25},{"idx":12,"close":1035.5},{"idx":13,"close":1035.75},{"idx":14,"close":1037},{"idx":15,"close":1036.5},{"idx":16,"close":1037},{"idx":17,"close":1037.5}],"bumpgroupcount":9,"bumpVolatilityData":{"bumpVolatilityPerc":0.23,"bumpVolatilityDiff":13.75,"bumpVolatilityIndex":17},"isNoBumpVolatility":true,"waves":0,"wavePoints":0,"isWaveOveride":false,"primariesLength":"none","confirmations":4,"isEnoughConfirmations":true,"enoughWaves":false,"notTradedBefore":false,"tradedBeforeTimestamp":1637938922853,"lastTimeTraded":"November 26, 2021 3:02 PM","tradedBeforeHoursDiff":0,"beforeRangeOveridden":false,"lastBeforeRangeTrendMovement":"bullish","lastBeforeRangeTrendMovementClose":989.75,"lastBeforeRangeTrendMovementTime":"2021-10-26 16:00:00","lastBeforeRangeTrendMovementDiff":20,"lastBeforeRangeTrendMovementPerc":7.82,"momentumLimit":5.88,"rangeLimit":26.46,"tradeLimit":17.64,"lineDistanceLimit":2.94,"priceDiff":58.8,"stopDistance":31.7,"stopDistanceLevel":1038.2,"limitDistance":15.85,"limitDistanceLevel":990.65,"ticket":{},"isDeal":false,"availableLoss":1919.0099999999998,"falseChecks":[{"___noBumpInRange":{"is":false,"enabled":true}},{"___recentTrendSameAsTrend":{"is":false,"enabled":true}},{"___rangeAreaGood":{"is":false,"enabled":true}},{"___enoughWaves":{"is":false,"enabled":true,"value":0}},{"___notTradedBefore":{"is":false,"enabled":true}},{"___recentTrendSameAs4HourTrend":{"is":false,"enabled":true}}],"trueChecks":[{"___4HoursNotRanging":{"is":true,"enabled":true}},{"___noVolatileGap":{"is":true,"enabled":true}},{"___breakingThroughRange":{"is":true,"enabled":true}},{"___withinTradeThreshold":{"is":true,"enabled":true}},{"___rangeConfirmationsGreaterThanLimit":{"is":true,"enabled":true}},{"___enoughConfirmations":{"is":true,"enabled":true}},{"___recentTrendPivoting":{"is":true,"enabled":true}},{"___lastCloseAboveBelowLines":{"is":true,"enabled":true}},{"___noBumpVolatility":{"is":true,"enabled":true}},{"___nolastPriceVolatile":{"is":true,"enabled":true}}]},"deal":{},"tradedBefore":1637938922853,"stopDistancePerc":0.4,"limitDistancePerc":0.2,"minimumStop":{"value":2,"type":"percentage"},"size":1},{"id":1,"alias":"MXNJPY","epic":"CS.D.MXNJPY.TODAY.IP","data":{"firstClose":535,"beforeRangeFirstClose":538.4,"firstDiff":"4.02","lastTime":"2021-11-26 15:00:00","lastOpen":521.2,"lastClose":518.8,"lastCloseAsk":519.2,"lastCloseBid":518.4,"lastHigh":521.2,"lastLow":518.2,"lastDiff":"1.02","nolastPriceVolatile":true,"lineData":{"support":513.5,"resistance":513.5,"midrange":513.5,"momentumLimitBuyLine":516.17,"momentumLimitSellLine":510.83,"tradeLimitBuyLine":521.51,"tradeLimitSellLine":505.49},"lineDistance":0,"previousTrend":"ranging","trend4Hours":"bearish","trend4HoursDiff":35.6,"trend4HoursDiffPerc":83.18,"first4HoursClose":554.4,"last4HoursClose":518.8,"highest4HourPrice":556.3,"lowest4HourPrice":513.5,"priceDiff4Hours":42.8,"is4HoursTrendOveride":false,"is4HoursNotRanging":true,"trend":"bearish","trendDiff":16.2,"trendDiffPerc":"312% (3.12)","beforeRangeTrend":"bearish","beforeRangeFirstCloseData":{"price":538.1,"open":538.1,"close":538.4,"high":538.7,"low":538,"diff":0,"time":"2021-11-25 03:00:00","closeAsk":538.8,"closeBid":538},"beforeRangeTrendDiff":19.6,"beforeRangeTrendDiffPerc":3.78,"rangedata_indexes":[12,13,14,15,16,17,18,19,20,21,22,23],"lastRangeData":{"price":518.8,"open":521.2,"close":518.8,"high":521.2,"low":518.2,"diff":2,"time":"2021-11-26 15:00:00","closeAsk":519.2,"closeBid":518.4},"recentrange":[13,14,15,16,17,18,19,20,21,22,23],"rangeConfirmations":12,"recentTrendArr":[{"movement":"down","open":521.7,"close":521},{"movement":"up","open":520.9,"close":524.2},{"movement":"up","open":524.1,"close":525.4},{"movement":"down","open":521.2,"close":518.8}],"recentTrend":"ranging","recentUps":2,"recentDowns":2,"recentMovementValue":-2.2,"recentMovementValueDiffPerc":"0.08%","isRangeAreaGood":false,"isRangeConfirmationsGreaterThanLimit":true,"isRecentRangeOverLimit":true,"recentRangeIndex21":8,"recentRangeIndex22":9,"recentRangeIndex23":10,"updatedtrend":"bearish","islastCloseAboveBelowLines":true,"isRecentTrendPivoting":true,"isRecentTrendSameAsTrend":false,"isBeforeRangeSameAsTrend":true,"isBeforeRangeTrendNotBroken":true,"isBeforeRangeSameAs4HourTrend":true,"isRecentTrendSameAs4HourTrend":false,"isBreakingThroughRange":true,"isWithinTradeThreshold":true,"isNoVolatileGap":true,"volatilityGapAnalysis":[],"totalMissingHours":1,"noBumpInRange":true,"bumps":[],"bumpgroupcount":0,"bumpVolatilityData":{"bumpVolatilityPerc":0,"bumpVolatilityDiff":0,"bumpVolatilityIndex":0},"isNoBumpVolatility":true,"waves":0,"wavePoints":0,"isWaveOveride":false,"primariesLength":"none","confirmations":2,"isEnoughConfirmations":true,"enoughWaves":false,"notTradedBefore":false,"tradedBeforeTimestamp":1637938976925,"lastTimeTraded":"November 26, 2021 3:02 PM","tradedBeforeHoursDiff":0,"beforeRangeOveridden":false,"lastBeforeRangeTrendMovement":"bearish","lastBeforeRangeTrendMovementClose":546.3,"lastBeforeRangeTrendMovementTime":"2021-04-29 11:00:00","lastBeforeRangeTrendMovementDiff":27.5,"lastBeforeRangeTrendMovementPerc":101.51,"momentumLimit":2.67,"rangeLimit":12.02,"tradeLimit":8.01,"lineDistanceLimit":1.33,"priceDiff":26.7,"stopDistance":17.12,"stopDistanceLevel":535.52,"limitDistance":8.56,"limitDistanceLevel":509.84,"ticket":{},"isDeal":false,"availableLoss":1919.0099999999998,"falseChecks":[{"___recentTrendSameAsTrend":{"is":false,"enabled":true}},{"___rangeAreaGood":{"is":false,"enabled":true}},{"___enoughWaves":{"is":false,"enabled":true,"value":0}},{"___notTradedBefore":{"is":false,"enabled":true}},{"___recentTrendSameAs4HourTrend":{"is":false,"enabled":true}}],"trueChecks":[{"___4HoursNotRanging":{"is":true,"enabled":true}},{"___noBumpInRange":{"is":true,"enabled":true}},{"___noVolatileGap":{"is":true,"enabled":true}},{"___breakingThroughRange":{"is":true,"enabled":true}},{"___withinTradeThreshold":{"is":true,"enabled":true}},{"___rangeConfirmationsGreaterThanLimit":{"is":true,"enabled":true}},{"___enoughConfirmations":{"is":true,"enabled":true,"note":"Overidden. trend4HoursDiffPerc is over 60% with 1 confirmation."}},{"___recentTrendPivoting":{"is":true,"enabled":true}},{"___lastCloseAboveBelowLines":{"is":true,"enabled":true}},{"___noBumpVolatility":{"is":true,"enabled":true}},{"___nolastPriceVolatile":{"is":true,"enabled":true}}]},"deal":{},"tradedBefore":1637938976925,"stopDistancePerc":0.4,"limitDistancePerc":0.2,"minimumStop":{"value":0.5,"type":"points"},"size":5,"marketClosed":[6,0]},{"id":2,"alias":"Spot Gold","epic":"CS.D.USCGC.TODAY.IP","data":{"firstClose":1793.11,"beforeRangeFirstClose":1788.27,"firstDiff":"0.22","lastTime":"2021-11-26 15:00:00","lastOpen":1798.62,"lastClose":1797.78,"lastCloseAsk":1798.03,"lastCloseBid":1797.53,"lastHigh":1802.73,"lastLow":1797.69,"lastDiff":"0.12","nolastPriceVolatile":true,"lineData":{"support":1789.12,"resistance":1795.66,"midrange":1792.39,"momentumLimitBuyLine":1798.75,"momentumLimitSellLine":1786.03,"tradeLimitBuyLine":1804.93,"tradeLimitSellLine":1779.85},"lineDistance":6.54,"previousTrend":"ranging","trend4Hours":"bearish","trend4HoursDiff":26.85,"trend4HoursDiffPerc":29.26,"first4HoursClose":1824.63,"last4HoursClose":1797.78,"highest4HourPrice":1870.36,"lowest4HourPrice":1778.59,"priceDiff4Hours":91.77,"is4HoursTrendOveride":false,"is4HoursNotRanging":true,"trend":"ranging","trendDiff":4.67,"trendDiffPerc":"26% (0.26)","beforeRangeTrend":"bullish","beforeRangeFirstCloseData":{"price":1784.94,"open":1784.94,"close":1788.27,"high":1788.63,"low":1784.72,"diff":3,"time":"2021-11-24 20:00:00","closeAsk":1788.52,"closeBid":1788.02},"beforeRangeTrendDiff":9.51,"beforeRangeTrendDiffPerc":0.53,"rangedata_indexes":[0,1,2,3,4,5,6,7,8,9,10,11,12],"lastRangeData":{"price":1794.23,"open":1794.23,"close":1797.09,"high":1798.83,"low":1794.23,"diff":3,"time":"2021-11-26 03:00:00","closeAsk":1797.34,"closeBid":1796.84},"recentrange":[],"rangeConfirmations":13,"recentTrendArr":[{"movement":"up","open":1809.72,"close":1811.8},{"movement":"down","open":1811.81,"close":1806.31},{"movement":"down","open":1806.3,"close":1805.71},{"movement":"down","open":1798.62,"close":1797.78}],"recentTrend":"bearish","recentUps":1,"recentDowns":3,"recentMovementValue":-14.02,"recentMovementValueDiffPerc":"0.45%","isRangeAreaGood":true,"isRangeConfirmationsGreaterThanLimit":true,"isRecentRangeOverLimit":false,"recentRangeIndex21":-1,"recentRangeIndex22":-1,"recentRangeIndex23":-1,"updatedtrend":"bearish","islastCloseAboveBelowLines":true,"isRecentTrendPivoting":true,"isRecentTrendSameAsTrend":true,"isBeforeRangeSameAsTrend":false,"isBeforeRangeTrendNotBroken":false,"isBeforeRangeSameAs4HourTrend":false,"isRecentTrendSameAs4HourTrend":true,"isBreakingThroughRange":false,"isWithinTradeThreshold":true,"isNoVolatileGap":true,"volatilityGapAnalysis":[],"totalMissingHours":8,"noBumpInRange":true,"bumps":[],"bumpgroupcount":0,"bumpVolatilityData":{"bumpVolatilityPerc":0,"bumpVolatilityDiff":0,"bumpVolatilityIndex":0},"isNoBumpVolatility":true,"waves":0,"wavePoints":3,"isWaveOveride":false,"primariesLength":5,"confirmations":3,"isEnoughConfirmations":true,"enoughWaves":false,"notTradedBefore":false,"tradedBeforeTimestamp":1637939042760,"lastTimeTraded":"November 26, 2021 3:04 PM","tradedBeforeHoursDiff":0,"beforeRangeOveridden":false,"lastBeforeRangeTrendMovement":"bearish","lastBeforeRangeTrendMovementClose":22.01,"lastBeforeRangeTrendMovementTime":"2021-03-31 16:00:00","lastBeforeRangeTrendMovementDiff":1775.77,"lastBeforeRangeTrendMovementPerc":5.97,"momentumLimit":3.09,"rangeLimit":13.9,"tradeLimit":9.27,"lineDistanceLimit":1.54,"priceDiff":30.89,"stopDistance":36.71,"stopDistanceLevel":1834.24,"limitDistance":18.35,"limitDistanceLevel":1779.18,"ticket":{},"isDeal":false,"availableLoss":1919.0099999999998,"falseChecks":[{"___breakingThroughRange":{"is":false,"enabled":true}},{"___enoughWaves":{"is":false,"enabled":true,"value":3}},{"___notTradedBefore":{"is":false,"enabled":true}}],"trueChecks":[{"___4HoursNotRanging":{"is":true,"enabled":true}},{"___noBumpInRange":{"is":true,"enabled":true}},{"___noVolatileGap":{"is":true,"enabled":true}},{"___withinTradeThreshold":{"is":true,"enabled":true}},{"___recentTrendSameAsTrend":{"is":true,"enabled":true}},{"___rangeConfirmationsGreaterThanLimit":{"is":true,"enabled":true}},{"___rangeAreaGood":{"is":true,"enabled":true}},{"___enoughConfirmations":{"is":true,"enabled":true}},{"___recentTrendPivoting":{"is":true,"enabled":true}},{"___lastCloseAboveBelowLines":{"is":true,"enabled":true}},{"___recentTrendSameAs4HourTrend":{"is":true,"enabled":true}},{"___noBumpVolatility":{"is":true,"enabled":true}},{"___nolastPriceVolatile":{"is":true,"enabled":true}}]},"deal":{},"tradedBefore":1637939042760,"stopDistancePerc":0.4,"limitDistancePerc":0.2,"minimumStop":{"value":2,"type":"points"},"size":1,"marketClosed":[6,0]},{"id":3,"alias":"Chicago Wheat","epic":"CC.D.W.USS.IP","data":{"firstClose":864.5,"beforeRangeFirstClose":857.9,"firstDiff":"0.46","lastTime":"2021-11-26 15:00:00","lastOpen":837.6,"lastClose":837.8,"lastCloseAsk":838.1,"lastCloseBid":837.5,"lastHigh":839.8,"lastLow":833.3,"lastDiff":"2.72","nolastPriceVolatile":true,"lineData":{"support":860.55,"resistance":871.2,"midrange":865.88,"momentumLimitBuyLine":875.32,"momentumLimitSellLine":856.43,"tradeLimitBuyLine":883.56,"tradeLimitSellLine":848.19},"lineDistance":10.65,"previousTrend":"ranging","trend4Hours":"bullish","trend4HoursDiff":64.1,"trend4HoursDiffPerc":63.84,"first4HoursClose":778.9,"last4HoursClose":843,"highest4HourPrice":874.5,"lowest4HourPrice":774.1,"priceDiff4Hours":100.4,"is4HoursTrendOveride":false,"is4HoursNotRanging":true,"trend":"bearish","trendDiff":26.7,"trendDiffPerc":"319% (3.19)","beforeRangeTrend":"bullish","beforeRangeFirstCloseData":{"price":857.9,"open":857.9,"close":857.9,"high":858.6,"low":857.9,"diff":0,"time":"2021-11-23 03:00:00","closeAsk":858.2,"closeBid":857.6},"beforeRangeTrendDiff":20.1,"beforeRangeTrendDiffPerc":2.4,"rangedata_indexes":[0,1,2,3,4,5,6,7,10,11,12,13,14,15,16,17],"lastRangeData":{"price":854.8,"open":866.3,"close":854.8,"high":867.1,"low":851.5,"diff":12,"time":"2021-11-24 15:00:00","closeAsk":855.1,"closeBid":854.5},"recentrange":[13,14,15,16,17],"rangeConfirmations":16,"recentTrendArr":[{"movement":"down","open":855,"close":851.8},{"movement":"up","open":851.9,"close":852.15},{"movement":"up","open":843,"close":843},{"movement":"up","open":837.6,"close":837.8}],"recentTrend":"bearish","recentUps":3,"recentDowns":1,"recentMovementValue":-14,"recentMovementValueDiffPerc":"0.34%","isRangeAreaGood":true,"isRangeConfirmationsGreaterThanLimit":true,"isRecentRangeOverLimit":true,"recentRangeIndex21":-1,"recentRangeIndex22":-1,"recentRangeIndex23":-1,"updatedtrend":"bearish","islastCloseAboveBelowLines":true,"isRecentTrendPivoting":true,"isRecentTrendSameAsTrend":true,"isBeforeRangeSameAsTrend":false,"isBeforeRangeTrendNotBroken":true,"isBeforeRangeSameAs4HourTrend":true,"isRecentTrendSameAs4HourTrend":false,"isBreakingThroughRange":false,"isWithinTradeThreshold":false,"isNoVolatileGap":true,"volatilityGapAnalysis":[],"totalMissingHours":49,"noBumpInRange":true,"bumps":[{"idx":8,"close":874.2}],"bumpgroupcount":0,"bumpVolatilityData":{"bumpVolatilityPerc":0,"bumpVolatilityDiff":0,"bumpVolatilityIndex":8},"isNoBumpVolatility":true,"waves":1,"wavePoints":4,"isWaveOveride":false,"primariesLength":5,"confirmations":0,"isEnoughConfirmations":false,"enoughWaves":false,"notTradedBefore":false,"tradedBeforeTimestamp":1637939094541,"lastTimeTraded":"November 26, 2021 3:04 PM","tradedBeforeHoursDiff":0,"beforeRangeOveridden":false,"lastBeforeRangeTrendMovement":"bearish","lastBeforeRangeTrendMovementClose":676.3,"lastBeforeRangeTrendMovementTime":"2021-07-01 08:00:00","lastBeforeRangeTrendMovementDiff":161.5,"lastBeforeRangeTrendMovementPerc":9.24,"momentumLimit":4.12,"rangeLimit":18.54,"tradeLimit":12.36,"lineDistanceLimit":2.06,"priceDiff":41.2,"stopDistance":40.16,"stopDistanceLevel":877.66,"limitDistance":20.08,"limitDistanceLevel":817.42,"ticket":{},"isDeal":false,"availableLoss":1919.0099999999998,"falseChecks":[{"___breakingThroughRange":{"is":false,"enabled":true}},{"___withinTradeThreshold":{"is":false,"enabled":true}},{"___enoughWaves":{"is":false,"enabled":true,"value":4}},{"___notTradedBefore":{"is":false,"enabled":true}},{"___enoughConfirmations":{"is":false,"enabled":true}},{"___recentTrendSameAs4HourTrend":{"is":false,"enabled":true}}],"trueChecks":[{"___4HoursNotRanging":{"is":true,"enabled":true}},{"___noBumpInRange":{"is":true,"enabled":true}},{"___noVolatileGap":{"is":true,"enabled":true}},{"___recentTrendSameAsTrend":{"is":true,"enabled":true}},{"___rangeConfirmationsGreaterThanLimit":{"is":true,"enabled":true}},{"___rangeAreaGood":{"is":true,"enabled":true}},{"___recentTrendPivoting":{"is":true,"enabled":true}},{"___lastCloseAboveBelowLines":{"is":true,"enabled":true}},{"___noBumpVolatility":{"is":true,"enabled":true}},{"___nolastPriceVolatile":{"is":true,"enabled":true}}]},"deal":{},"tradedBefore":1637939094541,"stopDistancePerc":0.4,"limitDistancePerc":0.2,"minimumStop":{"value":2.5,"type":"points"},"size":1,"marketClosed":[6,0],"test2":0,"test":0},{"id":4,"alias":"London Gas Oil","epic":"CC.D.LGO.USS.IP","data":{"firstClose":687,"beforeRangeFirstClose":688.7,"firstDiff":"2.22","lastTime":"2021-11-26 14:00:00","lastOpen":646.1,"lastClose":630.1,"lastCloseAsk":630.4,"lastCloseBid":629.8,"lastHigh":646.4,"lastLow":629.9,"lastDiff":"6.61","nolastPriceVolatile":true,"lineData":{"support":671.75,"resistance":689.33,"midrange":680.54,"momentumLimitBuyLine":695.43,"momentumLimitSellLine":665.65,"tradeLimitBuyLine":707.63,"tradeLimitSellLine":653.45},"lineDistance":17.58,"previousTrend":"ranging","trend4Hours":"bearish","trend4HoursDiff":68.3,"trend4HoursDiffPerc":89.52,"first4HoursClose":711.8,"last4HoursClose":643.5,"highest4HourPrice":717,"lowest4HourPrice":640.7,"priceDiff4Hours":76.3,"is4HoursTrendOveride":true,"is4HoursNotRanging":true,"trend":"bearish","trendDiff":56.9,"trendDiffPerc":"902.9999999999999% (9.03)","beforeRangeTrend":"ranging","beforeRangeFirstCloseData":{"price":688.4,"open":688.4,"close":688.7,"high":690,"low":686.8,"diff":0,"time":"2021-11-24 18:00:00","closeAsk":689,"closeBid":688.4},"beforeRangeTrendDiff":58.6,"beforeRangeTrendDiffPerc":9.3,"rangedata_indexes":[0,1,2,3,4,5,6,7,8,9,10,11,12,13],"lastRangeData":{"price":669.5,"open":674,"close":669.5,"high":674.1,"low":669.2,"diff":5,"time":"2021-11-26 04:00:00","closeAsk":669.8,"closeBid":669.2},"recentrange":[13],"rangeConfirmations":14,"recentTrendArr":[{"movement":"down","open":643.8,"close":643.5},{"movement":"down","open":643.4,"close":642.6},{"movement":"up","open":642.7,"close":646.4},{"movement":"down","open":646.1,"close":630.1}],"recentTrend":"bearish","recentUps":1,"recentDowns":3,"recentMovementValue":-13.4,"recentMovementValueDiffPerc":"0.22%","isRangeAreaGood":true,"isRangeConfirmationsGreaterThanLimit":true,"isRecentRangeOverLimit":false,"recentRangeIndex21":-1,"recentRangeIndex22":-1,"recentRangeIndex23":-1,"updatedtrend":"bearish","islastCloseAboveBelowLines":true,"isRecentTrendPivoting":true,"isRecentTrendSameAsTrend":true,"isBeforeRangeSameAsTrend":false,"isBeforeRangeTrendNotBroken":true,"isBeforeRangeSameAs4HourTrend":false,"isRecentTrendSameAs4HourTrend":true,"isBreakingThroughRange":false,"isWithinTradeThreshold":false,"isNoVolatileGap":true,"volatilityGapAnalysis":[],"totalMissingHours":9,"noBumpInRange":true,"bumps":[],"bumpgroupcount":0,"bumpVolatilityData":{"bumpVolatilityPerc":0,"bumpVolatilityDiff":0,"bumpVolatilityIndex":0},"isNoBumpVolatility":true,"waves":0,"wavePoints":2,"isWaveOveride":false,"primariesLength":2,"confirmations":3,"isEnoughConfirmations":true,"enoughWaves":false,"notTradedBefore":false,"tradedBeforeTimestamp":1637938862675,"lastTimeTraded":"November 26, 2021 3:01 PM","tradedBeforeHoursDiff":0,"beforeRangeOveridden":false,"lastBeforeRangeTrendMovement":"bearish","lastBeforeRangeTrendMovementClose":600.8,"lastBeforeRangeTrendMovementTime":"2021-07-15 16:00:00","lastBeforeRangeTrendMovementDiff":29.3,"lastBeforeRangeTrendMovementPerc":8.23,"momentumLimit":6.1,"rangeLimit":27.45,"tradeLimit":18.3,"lineDistanceLimit":3.05,"priceDiff":61,"stopDistance":30.52,"stopDistanceLevel":660.32,"limitDistance":15.26,"limitDistanceLevel":614.54,"ticket":{},"isDeal":false,"availableLoss":1919.0099999999998,"falseChecks":[{"___breakingThroughRange":{"is":false,"enabled":true}},{"___withinTradeThreshold":{"is":false,"enabled":true}},{"___enoughWaves":{"is":false,"enabled":true,"value":2}},{"___notTradedBefore":{"is":false,"enabled":true}}],"trueChecks":[{"___4HoursNotRanging":{"is":true,"enabled":true}},{"___noBumpInRange":{"is":true,"enabled":true}},{"___noVolatileGap":{"is":true,"enabled":true}},{"___recentTrendSameAsTrend":{"is":true,"enabled":true}},{"___rangeConfirmationsGreaterThanLimit":{"is":true,"enabled":true}},{"___rangeAreaGood":{"is":true,"enabled":true}},{"___enoughConfirmations":{"is":true,"enabled":true,"note":"Overidden. trend4HoursDiffPerc is over 60% with 1 confirmation."}},{"___recentTrendPivoting":{"is":true,"enabled":true}},{"___lastCloseAboveBelowLines":{"is":true,"enabled":true}},{"___recentTrendSameAs4HourTrend":{"is":true,"enabled":true}},{"___noBumpVolatility":{"is":true,"enabled":true}},{"___nolastPriceVolatile":{"is":true,"enabled":true}}]},"deal":{},"tradedBefore":1637938862675,"stopDistancePerc":0.4,"limitDistancePerc":0.2,"minimumStop":{"value":1.5,"type":"points"},"size":1,"marketClosed":[7,0],"test":0}]