[{"id":0,"alias":"Volatility Index","epic":"CC.D.VIX.USS.IP","data":{"firstClose":18.39,"beforeRangeFirstClose":18.7,"firstDiff":"0.76","lastTime":"2021-06-29 04:00:00","lastOpen":18.56,"lastClose":18.57,"lastCloseAsk":18.65,"lastCloseBid":18.49,"lastHigh":18.57,"lastLow":18.56,"lastDiff":"1.72","lineData":{"support":18.25,"resistance":18.25,"midrange":18.25,"momentumLimitBuyLine":18.3,"momentumLimitSellLine":18.2,"tradeLimitBuyLine":18.4,"tradeLimitSellLine":18.1},"lineDistance":0,"previousTrend":"ranging","trend4Hours":"bearish","trend4HoursDiff":0.83,"trend4HoursDiffPerc":20.05,"first4HoursClose":19.36,"last4HoursClose":18.53,"highest4HourPrice":22.39,"lowest4HourPrice":18.25,"priceDiff4Hours":4.14,"is4HoursTrendOveride":false,"is4HoursNotRanging":true,"trend":"ranging","trendDiff":0.18,"trendDiffPerc":"97% (0.97)","beforeRangeTrend":"bearish","beforeRangeFirstCloseData":{"price":18.7,"open":18.7,"close":18.7,"high":18.74,"low":18.65,"diff":0,"time":"2021-06-25 12:00:00","closeAsk":18.78,"closeBid":18.62},"beforeRangeTrendDiff":0.13,"beforeRangeTrendDiffPerc":0.7,"rangedata_indexes":[0,1,2,3,5,6,7,8,12,13,16,17,18,19,20],"lastRangeData":{"price":18.48,"open":18.5,"close":18.48,"high":18.53,"low":18.48,"diff":0,"time":"2021-06-29 01:00:00","closeAsk":18.56,"closeBid":18.4},"recentrange":[13,16,17,18,19,20],"rangeConfirmations":15,"recentTrendArr":[{"movement":"down","open":18.5,"close":18.48},{"movement":"up","open":18.53,"close":18.53},{"movement":"down","open":18.56,"close":18.53},{"movement":"up","open":18.56,"close":18.57}],"recentTrend":"bullish","recentUps":2,"recentDowns":2,"recentMovementValue":0.09,"recentMovementValueDiffPerc":"0.18%","isRangeAreaGood":false,"isRangeConfirmationsGreaterThanLimit":true,"isRecentRangeOverLimit":true,"recentRangeIndex21":-1,"recentRangeIndex22":-1,"recentRangeIndex23":-1,"updatedtrend":"bearish","islastCloseAboveBelowLines":true,"isRecentTrendPivoting":true,"isRecentTrendSameAsTrend":false,"isBeforeRangeSameAsTrend":true,"isBeforeRangeTrendNotBroken":true,"isBeforeRangeSameAs4HourTrend":true,"isRecentTrendSameAs4HourTrend":false,"isBreakingThroughRange":false,"isWithinTradeThreshold":true,"isNoVolatileGap":true,"volatilityGapAnalysis":[],"totalMissingHours":53,"noBumpInRange":true,"bumps":[{"idx":4,"close":18.35},{"idx":9,"close":18.31},{"idx":10,"close":18.3},{"idx":11,"close":18.35},{"idx":14,"close":18.57},{"idx":15,"close":18.54}],"bumpgroupcount":3,"bumpVolatilityData":{"bumpVolatilityPerc":0.1,"bumpVolatilityDiff":0.05,"bumpVolatilityIndex":15},"isNoBumpVolatility":true,"waves":0,"wavePoints":0,"confirmations":2,"isEnoughConfirmations":true,"enoughWaves":false,"notTradedBefore":true,"tradedBeforeTimestamp":false,"lastTimeTraded":false,"tradedBeforeHoursDiff":false,"beforeRangeOveridden":false,"lastBeforeRangeTrendMovement":"bullish","lastBeforeRangeTrendMovementClose":0,"lastBeforeRangeTrendMovementTime":"2021-04-09 00:00:00","lastBeforeRangeTrendMovementDiff":18.57,"lastBeforeRangeTrendMovementPerc":100,"momentumLimit":0.05,"rangeLimit":0.22,"tradeLimit":0.15,"lineDistanceLimit":0.02,"priceDiff":0.49,"stopDistance":0.15,"stopDistanceLevel":18.64,"limitDistance":0.1,"limitDistanceLevel":18.39,"ticket":{},"isDeal":false,"falseChecks":[{"___breakingThroughRange":{"is":false}},{"___recentTrendSameAsTrend":{"is":false}},{"___rangeAreaGood":{"is":false}},{"___enoughWaves":{"is":false,"value":0}},{"___recentTrendSameAs4HourTrend":{"is":false}}],"trueChecks":[{"___4HoursNotRanging":{"is":true}},{"___noBumpInRange":{"is":true}},{"___noVolatileGap":{"is":true}},{"___withinTradeThreshold":{"is":true}},{"___beforeRangeTrendNotBroken":{"is":true}},{"___beforeRangeSameAsTrend":{"is":true}},{"___rangeConfirmationsGreaterThanLimit":{"is":true}},{"___notTradedBefore":{"is":true}},{"___enoughConfirmations":{"is":true}},{"___recentTrendPivoting":{"is":true}},{"___lastCloseAboveBelowLines":{"is":true}},{"___beforeRangeSameAs4HourTrend":{"is":true}},{"___noBumpVolatility":{"is":true}}]},"deal":{},"tradedBefore":false,"stopDistancePerc":"0.3","limitDistancePerc":0.2,"minimumStop":{"value":0.2,"type":"points"},"size":5,"marketClosed":[6,0]},{"id":1,"alias":"MXNJPY","epic":"CS.D.MXNJPY.TODAY.IP","data":{"firstClose":558,"beforeRangeFirstClose":559.7,"firstDiff":"0.07","lastTime":"2021-06-29 04:00:00","lastOpen":557.2,"lastClose":557.2,"lastCloseAsk":557.6,"lastCloseBid":556.8,"lastHigh":557.4,"lastLow":557,"lastDiff":"0.07","lineData":{"support":557.6,"resistance":558.5,"midrange":558.05,"momentumLimitBuyLine":558.9,"momentumLimitSellLine":557.2,"tradeLimitBuyLine":559.69,"tradeLimitSellLine":556.41},"lineDistance":0.9,"previousTrend":"ranging","trend4Hours":"bullish","trend4HoursDiff":5.9,"trend4HoursDiffPerc":18.32,"first4HoursClose":552,"last4HoursClose":557.9,"highest4HourPrice":562.2,"lowest4HourPrice":530,"priceDiff4Hours":32.2,"is4HoursTrendOveride":false,"is4HoursNotRanging":true,"trend":"ranging","trendDiff":0.8,"trendDiffPerc":"14.000000000000002% (0.14)","beforeRangeTrend":"bearish","beforeRangeFirstCloseData":{"price":559.7,"open":560.2,"close":559.7,"high":560.65,"low":559.55,"diff":1,"time":"2021-06-25 18:00:00","closeAsk":560,"closeBid":559.4},"beforeRangeTrendDiff":2.5,"beforeRangeTrendDiffPerc":0.45,"rangedata_indexes":[0,1,4,5,7,8,9,12,13,14,15,16,17,18,19,20,21],"lastRangeData":{"price":557.5,"open":557.7,"close":557.5,"high":557.8,"low":557.4,"diff":0,"time":"2021-06-29 02:00:00","closeAsk":557.9,"closeBid":557.1},"recentrange":[13,14,15,16,17,18,19,20,21],"rangeConfirmations":17,"recentTrendArr":[{"movement":"down","open":558.2,"close":557.8},{"movement":"down","open":557.7,"close":557.5},{"movement":"down","open":557.6,"close":557.3},{"movement":"up","open":557.2,"close":557.2}],"recentTrend":"bearish","recentUps":1,"recentDowns":3,"recentMovementValue":-0.6,"recentMovementValueDiffPerc":"0.15%","isRangeAreaGood":true,"isRangeConfirmationsGreaterThanLimit":true,"isRecentRangeOverLimit":true,"recentRangeIndex21":8,"recentRangeIndex22":-1,"recentRangeIndex23":-1,"updatedtrend":"bullish","islastCloseAboveBelowLines":true,"isRecentTrendPivoting":true,"isRecentTrendSameAsTrend":false,"isBeforeRangeSameAsTrend":false,"isBeforeRangeTrendNotBroken":true,"isBeforeRangeSameAs4HourTrend":false,"isRecentTrendSameAs4HourTrend":false,"isBreakingThroughRange":true,"isWithinTradeThreshold":true,"isNoVolatileGap":true,"volatilityGapAnalysis":[],"totalMissingHours":47,"noBumpInRange":true,"bumps":[{"idx":2,"close":559},{"idx":6,"close":557.3},{"idx":10,"close":559.3},{"idx":11,"close":558.7}],"bumpgroupcount":1,"bumpVolatilityData":{"bumpVolatilityPerc":0.15,"bumpVolatilityDiff":0.6,"bumpVolatilityIndex":11},"isNoBumpVolatility":true,"waves":3,"wavePoints":8,"confirmations":1,"isEnoughConfirmations":false,"enoughWaves":true,"notTradedBefore":true,"tradedBeforeTimestamp":false,"lastTimeTraded":false,"tradedBeforeHoursDiff":false,"beforeRangeOveridden":false,"lastBeforeRangeTrendMovement":"bearish","lastBeforeRangeTrendMovementClose":546.3,"lastBeforeRangeTrendMovementTime":"2021-04-29 11:00:00","lastBeforeRangeTrendMovementDiff":10.9,"lastBeforeRangeTrendMovementPerc":101.51,"momentumLimit":0.4,"rangeLimit":1.78,"tradeLimit":1.19,"lineDistanceLimit":0.2,"priceDiff":3.95,"stopDistance":1.19,"stopDistanceLevel":556.41,"limitDistance":0.79,"limitDistanceLevel":558.39,"ticket":{},"isDeal":false,"falseChecks":[{"___recentTrendSameAsTrend":{"is":false}},{"___beforeRangeSameAsTrend":{"is":false}},{"___enoughConfirmations":{"is":false}},{"___beforeRangeSameAs4HourTrend":{"is":false}},{"___recentTrendSameAs4HourTrend":{"is":false}}],"trueChecks":[{"___4HoursNotRanging":{"is":true}},{"___noBumpInRange":{"is":true}},{"___noVolatileGap":{"is":true}},{"___breakingThroughRange":{"is":true}},{"___withinTradeThreshold":{"is":true}},{"___beforeRangeTrendNotBroken":{"is":true}},{"___rangeConfirmationsGreaterThanLimit":{"is":true}},{"___rangeAreaGood":{"is":true}},{"___enoughWaves":{"is":true,"value":8}},{"___notTradedBefore":{"is":true}},{"___recentTrendPivoting":{"is":true}},{"___lastCloseAboveBelowLines":{"is":true}},{"___noBumpVolatility":{"is":true}}]},"deal":{},"tradedBefore":false,"stopDistancePerc":"0.3","limitDistancePerc":0.2,"minimumStop":{"value":2,"type":"points"},"size":5,"marketClosed":[6,0]},{"id":2,"alias":"Spot Gold","epic":"CS.D.USCGC.TODAY.IP","data":{"firstClose":1779.24,"beforeRangeFirstClose":1782.03,"firstDiff":"0.16","lastTime":"2021-06-29 04:00:00","lastOpen":1775.94,"lastClose":1775.28,"lastCloseAsk":1775.53,"lastCloseBid":1775.03,"lastHigh":1776.38,"lastLow":1774.13,"lastDiff":"0.07","lineData":{"support":1776.45,"resistance":1780.28,"midrange":1778.37,"momentumLimitBuyLine":1782.04,"momentumLimitSellLine":1774.69,"tradeLimitBuyLine":1785.57,"tradeLimitSellLine":1771.16},"lineDistance":3.83,"previousTrend":"ranging","trend4Hours":"bearish","trend4HoursDiff":76.69,"trend4HoursDiffPerc":70.34,"first4HoursClose":1854.72,"last4HoursClose":1778.03,"highest4HourPrice":1869.88,"lowest4HourPrice":1760.85,"priceDiff4Hours":109.03,"is4HoursTrendOveride":true,"is4HoursNotRanging":true,"trend":"ranging","trendDiff":3.96,"trendDiffPerc":"22% (0.22)","beforeRangeTrend":"bearish","beforeRangeFirstCloseData":{"price":1782.03,"open":1788.31,"close":1782.03,"high":1788.39,"low":1781.37,"diff":6,"time":"2021-06-25 15:00:00","closeAsk":1782.28,"closeBid":1781.78},"beforeRangeTrendDiff":6.75,"beforeRangeTrendDiffPerc":0.38,"rangedata_indexes":[6,7,8,10,11,12,13,14,15,16,17,18,19,20],"lastRangeData":{"price":1775.85,"open":1778.18,"close":1775.85,"high":1778.31,"low":1775.28,"diff":2,"time":"2021-06-29 01:00:00","closeAsk":1776.1,"closeBid":1775.6},"recentrange":[13,14,15,16,17,18,19,20],"rangeConfirmations":14,"recentTrendArr":[{"movement":"down","open":1778.18,"close":1775.85},{"movement":"down","open":1775.84,"close":1774.57},{"movement":"up","open":1774.62,"close":1775.93},{"movement":"down","open":1775.94,"close":1775.28}],"recentTrend":"bearish","recentUps":1,"recentDowns":3,"recentMovementValue":-0.57,"recentMovementValueDiffPerc":"0.03%","isRangeAreaGood":true,"isRangeConfirmationsGreaterThanLimit":true,"isRecentRangeOverLimit":true,"recentRangeIndex21":-1,"recentRangeIndex22":-1,"recentRangeIndex23":-1,"updatedtrend":"bearish","islastCloseAboveBelowLines":true,"isRecentTrendPivoting":true,"isRecentTrendSameAsTrend":true,"isBeforeRangeSameAsTrend":true,"isBeforeRangeTrendNotBroken":true,"isBeforeRangeSameAs4HourTrend":true,"isRecentTrendSameAs4HourTrend":true,"isBreakingThroughRange":false,"isWithinTradeThreshold":true,"isNoVolatileGap":true,"volatilityGapAnalysis":[],"totalMissingHours":50,"noBumpInRange":true,"bumps":[],"bumpgroupcount":0,"bumpVolatilityData":{"bumpVolatilityPerc":0,"bumpVolatilityDiff":0,"bumpVolatilityIndex":0},"isNoBumpVolatility":true,"waves":4,"wavePoints":9,"confirmations":1,"isEnoughConfirmations":false,"enoughWaves":true,"notTradedBefore":true,"tradedBeforeTimestamp":false,"lastTimeTraded":false,"tradedBeforeHoursDiff":false,"beforeRangeOveridden":false,"lastBeforeRangeTrendMovement":"bearish","lastBeforeRangeTrendMovementClose":22.01,"lastBeforeRangeTrendMovementTime":"2021-03-31 16:00:00","lastBeforeRangeTrendMovementDiff":1753.27,"lastBeforeRangeTrendMovementPerc":5.97,"momentumLimit":1.76,"rangeLimit":7.94,"tradeLimit":5.29,"lineDistanceLimit":0.88,"priceDiff":17.65,"stopDistance":5.29,"stopDistanceLevel":1780.32,"limitDistance":3.53,"limitDistanceLevel":1771.5,"ticket":{},"isDeal":false,"falseChecks":[{"___breakingThroughRange":{"is":false}},{"___enoughConfirmations":{"is":false}}],"trueChecks":[{"___4HoursNotRanging":{"is":true}},{"___noBumpInRange":{"is":true}},{"___noVolatileGap":{"is":true}},{"___withinTradeThreshold":{"is":true}},{"___beforeRangeTrendNotBroken":{"is":true}},{"___recentTrendSameAsTrend":{"is":true}},{"___beforeRangeSameAsTrend":{"is":true}},{"___rangeConfirmationsGreaterThanLimit":{"is":true}},{"___rangeAreaGood":{"is":true}},{"___enoughWaves":{"is":true,"value":9}},{"___notTradedBefore":{"is":true}},{"___recentTrendPivoting":{"is":true}},{"___lastCloseAboveBelowLines":{"is":true}},{"___beforeRangeSameAs4HourTrend":{"is":true}},{"___recentTrendSameAs4HourTrend":{"is":true}},{"___noBumpVolatility":{"is":true}}]},"deal":{},"tradedBefore":false,"stopDistancePerc":"0.3","limitDistancePerc":0.2,"minimumStop":{"value":1,"type":"points"},"size":5,"marketClosed":[6,0]},{"id":3,"alias":"Chicago Wheat","epic":"CC.D.W.USS.IP","data":{"firstClose":637.6,"beforeRangeFirstClose":652.3,"firstDiff":"1.87","lastTime":"2021-06-29 04:00:00","lastOpen":653,"lastClose":651.4,"lastCloseAsk":651.7,"lastCloseBid":651.1,"lastHigh":653.4,"lastLow":650.9,"lastDiff":"0.29","lineData":{"support":649.5,"resistance":655.3,"midrange":652.4,"momentumLimitBuyLine":657.55,"momentumLimitSellLine":647.25,"tradeLimitBuyLine":662.05,"tradeLimitSellLine":642.75},"lineDistance":5.8,"previousTrend":"ranging","trend4Hours":"bearish","trend4HoursDiff":25.1,"trend4HoursDiffPerc":45.89,"first4HoursClose":682.2,"last4HoursClose":657.1,"highest4HourPrice":691.8,"lowest4HourPrice":637.1,"priceDiff4Hours":54.7,"is4HoursTrendOveride":false,"is4HoursNotRanging":true,"trend":"bullish","trendDiff":13.8,"trendDiffPerc":"212% (2.12)","beforeRangeTrend":"ranging","beforeRangeFirstCloseData":{"price":651.4,"open":651.4,"close":652.3,"high":653,"low":651.2,"diff":1,"time":"2021-06-25 07:00:00","closeAsk":652.6,"closeBid":652},"beforeRangeTrendDiff":0.9,"beforeRangeTrendDiffPerc":0.14,"rangedata_indexes":[10,11,12,13,14,15,16,17,18,19,21,22,23],"lastRangeData":{"price":651.4,"open":653,"close":651.4,"high":653.4,"low":650.9,"diff":2,"time":"2021-06-29 04:00:00","closeAsk":651.7,"closeBid":651.1},"recentrange":[13,14,15,16,17,18,19,21,22,23],"rangeConfirmations":13,"recentTrendArr":[{"movement":"down","open":657.4,"close":657.1},{"movement":"up","open":652.7,"close":653.9},{"movement":"down","open":654,"close":652.9},{"movement":"down","open":653,"close":651.4}],"recentTrend":"bearish","recentUps":1,"recentDowns":3,"recentMovementValue":-5.7,"recentMovementValueDiffPerc":"0.25%","isRangeAreaGood":true,"isRangeConfirmationsGreaterThanLimit":true,"isRecentRangeOverLimit":true,"recentRangeIndex21":7,"recentRangeIndex22":8,"recentRangeIndex23":9,"updatedtrend":"bullish","islastCloseAboveBelowLines":false,"isRecentTrendPivoting":true,"isRecentTrendSameAsTrend":false,"isBeforeRangeSameAsTrend":true,"isBeforeRangeTrendNotBroken":false,"isBeforeRangeSameAs4HourTrend":false,"isRecentTrendSameAs4HourTrend":true,"isBreakingThroughRange":true,"isWithinTradeThreshold":true,"isNoVolatileGap":true,"volatilityGapAnalysis":[],"totalMissingHours":58,"noBumpInRange":true,"bumps":[{"idx":20,"close":657.1}],"bumpgroupcount":0,"bumpVolatilityData":{"bumpVolatilityPerc":0,"bumpVolatilityDiff":0,"bumpVolatilityIndex":20},"isNoBumpVolatility":true,"waves":2,"wavePoints":5,"confirmations":1,"isEnoughConfirmations":false,"enoughWaves":true,"notTradedBefore":true,"tradedBeforeTimestamp":false,"lastTimeTraded":false,"tradedBeforeHoursDiff":false,"beforeRangeOveridden":true,"lastBeforeRangeTrendMovement":"bullish","lastBeforeRangeTrendMovementClose":681.2,"lastBeforeRangeTrendMovementTime":"2021-04-22 13:00:00","lastBeforeRangeTrendMovementDiff":29.8,"lastBeforeRangeTrendMovementPerc":7.46,"momentumLimit":2.25,"rangeLimit":10.13,"tradeLimit":6.75,"lineDistanceLimit":1.13,"priceDiff":22.5,"stopDistance":6.75,"stopDistanceLevel":644.95,"limitDistance":4.5,"limitDistanceLevel":656.2,"ticket":{},"isDeal":false,"falseChecks":[{"___beforeRangeTrendNotBroken":{"is":false}},{"___recentTrendSameAsTrend":{"is":false}},{"___enoughConfirmations":{"is":false}},{"___lastCloseAboveBelowLines":{"is":false}},{"___beforeRangeSameAs4HourTrend":{"is":false}}],"trueChecks":[{"___4HoursNotRanging":{"is":true}},{"___noBumpInRange":{"is":true}},{"___noVolatileGap":{"is":true}},{"___breakingThroughRange":{"is":true}},{"___withinTradeThreshold":{"is":true}},{"___beforeRangeSameAsTrend":{"is":true}},{"___rangeConfirmationsGreaterThanLimit":{"is":true}},{"___rangeAreaGood":{"is":true}},{"___enoughWaves":{"is":true,"value":5}},{"___notTradedBefore":{"is":true}},{"___recentTrendPivoting":{"is":true}},{"___recentTrendSameAs4HourTrend":{"is":true}},{"___noBumpVolatility":{"is":true}}]},"deal":{},"tradedBefore":false,"stopDistancePerc":"0.3","limitDistancePerc":0.2,"minimumStop":{"value":2.5,"type":"points"},"size":5,"marketClosed":[6,0],"test2":0,"test":0},{"id":4,"alias":"London Gas Oil","epic":"CC.D.LGO.USS.IP","data":{"firstClose":610.7,"beforeRangeFirstClose":605.8,"firstDiff":"0.17","lastTime":"2021-06-29 03:00:00","lastOpen":597.2,"lastClose":596.3,"lastCloseAsk":596.6,"lastCloseBid":596,"lastHigh":597.3,"lastLow":596.3,"lastDiff":"1.52","lineData":{"support":605.35,"resistance":609.65,"midrange":607.5,"momentumLimitBuyLine":611.21,"momentumLimitSellLine":603.79,"tradeLimitBuyLine":614.33,"tradeLimitSellLine":600.67},"lineDistance":4.3,"previousTrend":"ranging","trend4Hours":"bullish","trend4HoursDiff":6.5,"trend4HoursDiffPerc":22.73,"first4HoursClose":590.5,"last4HoursClose":597,"highest4HourPrice":611.4,"lowest4HourPrice":582.8,"priceDiff4Hours":28.6,"is4HoursTrendOveride":false,"is4HoursNotRanging":true,"trend":"bearish","trendDiff":14.4,"trendDiffPerc":"241% (2.41)","beforeRangeTrend":"ranging","beforeRangeFirstCloseData":{"price":605.8,"open":607.7,"close":605.8,"high":607.7,"low":605.8,"diff":2,"time":"2021-06-25 07:00:00","closeAsk":606.1,"closeBid":605.5},"beforeRangeTrendDiff":9.5,"beforeRangeTrendDiffPerc":1.59,"rangedata_indexes":[1,2,3,4,5,6,7,8,9,10,11,12,13],"lastRangeData":{"price":602.8,"open":607.9,"close":602.8,"high":608.4,"low":601.4,"diff":5,"time":"2021-06-28 14:00:00","closeAsk":603.1,"closeBid":602.5},"recentrange":[13],"rangeConfirmations":13,"recentTrendArr":[{"movement":"down","open":598.2,"close":598.1},{"movement":"down","open":598,"close":597.85},{"movement":"down","open":597.5,"close":597},{"movement":"down","open":597.2,"close":596.3}],"recentTrend":"bearish","recentUps":0,"recentDowns":4,"recentMovementValue":-1.8,"recentMovementValueDiffPerc":"0.12%","isRangeAreaGood":true,"isRangeConfirmationsGreaterThanLimit":true,"isRecentRangeOverLimit":false,"recentRangeIndex21":-1,"recentRangeIndex22":-1,"recentRangeIndex23":-1,"updatedtrend":"bearish","islastCloseAboveBelowLines":true,"isRecentTrendPivoting":true,"isRecentTrendSameAsTrend":true,"isBeforeRangeSameAsTrend":false,"isBeforeRangeTrendNotBroken":false,"isBeforeRangeSameAs4HourTrend":false,"isRecentTrendSameAs4HourTrend":false,"isBreakingThroughRange":false,"isWithinTradeThreshold":false,"isNoVolatileGap":true,"volatilityGapAnalysis":[],"totalMissingHours":57,"noBumpInRange":true,"bumps":[],"bumpgroupcount":0,"bumpVolatilityData":{"bumpVolatilityPerc":0,"bumpVolatilityDiff":0,"bumpVolatilityIndex":0},"isNoBumpVolatility":true,"waves":1,"wavePoints":4,"confirmations":1,"isEnoughConfirmations":false,"enoughWaves":true,"notTradedBefore":true,"tradedBeforeTimestamp":false,"lastTimeTraded":false,"tradedBeforeHoursDiff":false,"beforeRangeOveridden":false,"lastBeforeRangeTrendMovement":"bearish","lastBeforeRangeTrendMovementClose":513,"lastBeforeRangeTrendMovementTime":"2021-03-22 06:00:00","lastBeforeRangeTrendMovementDiff":83.3,"lastBeforeRangeTrendMovementPerc":5.89,"momentumLimit":1.56,"rangeLimit":7.02,"tradeLimit":4.68,"lineDistanceLimit":0.78,"priceDiff":15.6,"stopDistance":4.68,"stopDistanceLevel":600.68,"limitDistance":3.12,"limitDistanceLevel":592.88,"ticket":{},"isDeal":false,"falseChecks":[{"___breakingThroughRange":{"is":false}},{"___withinTradeThreshold":{"is":false}},{"___beforeRangeTrendNotBroken":{"is":false}},{"___beforeRangeSameAsTrend":{"is":false}},{"___enoughConfirmations":{"is":false}},{"___beforeRangeSameAs4HourTrend":{"is":false}},{"___recentTrendSameAs4HourTrend":{"is":false}}],"trueChecks":[{"___4HoursNotRanging":{"is":true}},{"___noBumpInRange":{"is":true}},{"___noVolatileGap":{"is":true}},{"___recentTrendSameAsTrend":{"is":true}},{"___rangeConfirmationsGreaterThanLimit":{"is":true}},{"___rangeAreaGood":{"is":true}},{"___enoughWaves":{"is":true,"value":4}},{"___notTradedBefore":{"is":true}},{"___recentTrendPivoting":{"is":true}},{"___lastCloseAboveBelowLines":{"is":true}},{"___noBumpVolatility":{"is":true}}]},"deal":{},"tradedBefore":false,"stopDistancePerc":"0.3","limitDistancePerc":0.2,"minimumStop":{"value":1.5,"type":"points"},"size":5,"marketClosed":[7,0],"test":0}]