[{"snapshotTime":"2022/10/31 04:00:00","openPrice":{"bid":890,"ask":890.6,"lastTraded":null},"closePrice":{"bid":886.6,"ask":887.2,"lastTraded":null},"highPrice":{"bid":890.3,"ask":891,"lastTraded":null},"lowPrice":{"bid":885.8,"ask":886.4,"lastTraded":null},"lastTradedVolume":167},{"snapshotTime":"2022/10/31 05:00:00","openPrice":{"bid":887.4,"ask":888,"lastTraded":null},"closePrice":{"bid":887,"ask":887.6,"lastTraded":null},"highPrice":{"bid":888.4,"ask":889.2,"lastTraded":null},"lowPrice":{"bid":886,"ask":886.8,"lastTraded":null},"lastTradedVolume":394},{"snapshotTime":"2022/10/31 06:00:00","openPrice":{"bid":888,"ask":888.6,"lastTraded":null},"closePrice":{"bid":891.7,"ask":892.3,"lastTraded":null},"highPrice":{"bid":892.3,"ask":892.9,"lastTraded":null},"lowPrice":{"bid":886.8,"ask":887.8,"lastTraded":null},"lastTradedVolume":445},{"snapshotTime":"2022/10/31 07:00:00","openPrice":{"bid":891.6,"ask":892.2,"lastTraded":null},"closePrice":{"bid":889.4,"ask":890.4,"lastTraded":null},"highPrice":{"bid":892.2,"ask":892.8,"lastTraded":null},"lowPrice":{"bid":886.3,"ask":886.9,"lastTraded":null},"lastTradedVolume":813},{"snapshotTime":"2022/10/31 09:00:00","openPrice":{"bid":891.6,"ask":892.2,"lastTraded":null},"closePrice":{"bid":889.7,"ask":890.3,"lastTraded":null},"highPrice":{"bid":896.7,"ask":897.3,"lastTraded":null},"lowPrice":{"bid":889.2,"ask":889.9,"lastTraded":null},"lastTradedVolume":1210},{"snapshotTime":"2022/10/31 10:00:00","openPrice":{"bid":889.8,"ask":890.4,"lastTraded":null},"closePrice":{"bid":891.3,"ask":891.9,"lastTraded":null},"highPrice":{"bid":891.6,"ask":892.2,"lastTraded":null},"lowPrice":{"bid":888.8,"ask":889.4,"lastTraded":null},"lastTradedVolume":518},{"snapshotTime":"2022/10/31 11:00:00","openPrice":{"bid":891.4,"ask":892,"lastTraded":null},"closePrice":{"bid":887.5,"ask":888.1,"lastTraded":null},"highPrice":{"bid":892.2,"ask":892.8,"lastTraded":null},"lowPrice":{"bid":884.5,"ask":885.1,"lastTraded":null},"lastTradedVolume":964},{"snapshotTime":"2022/10/31 12:00:00","openPrice":{"bid":887.6,"ask":888.2,"lastTraded":null},"closePrice":{"bid":886.5,"ask":887.1,"lastTraded":null},"highPrice":{"bid":892.1,"ask":892.7,"lastTraded":null},"lowPrice":{"bid":886.4,"ask":887.1,"lastTraded":null},"lastTradedVolume":1035},{"snapshotTime":"2022/10/31 13:00:00","openPrice":{"bid":887,"ask":887.6,"lastTraded":null},"closePrice":{"bid":892.6,"ask":893.2,"lastTraded":null},"highPrice":{"bid":894.6,"ask":895.2,"lastTraded":null},"lowPrice":{"bid":876.3,"ask":877.1,"lastTraded":null},"lastTradedVolume":7479},{"snapshotTime":"2022/10/31 14:00:00","openPrice":{"bid":892.7,"ask":893.3,"lastTraded":null},"closePrice":{"bid":887,"ask":887.6,"lastTraded":null},"highPrice":{"bid":897.3,"ask":897.9,"lastTraded":null},"lowPrice":{"bid":886.6,"ask":887.4,"lastTraded":null},"lastTradedVolume":7474},{"snapshotTime":"2022/10/31 15:00:00","openPrice":{"bid":887.1,"ask":887.7,"lastTraded":null},"closePrice":{"bid":867,"ask":867.6,"lastTraded":null},"highPrice":{"bid":888.1,"ask":888.7,"lastTraded":null},"lowPrice":{"bid":866.7,"ask":867.3,"lastTraded":null},"lastTradedVolume":8641},{"snapshotTime":"2022/10/31 16:00:00","openPrice":{"bid":867.2,"ask":867.8,"lastTraded":null},"closePrice":{"bid":882.3,"ask":882.9,"lastTraded":null},"highPrice":{"bid":882.5,"ask":883.1,"lastTraded":null},"lowPrice":{"bid":866.7,"ask":867.3,"lastTraded":null},"lastTradedVolume":7035},{"snapshotTime":"2022/10/31 17:00:00","openPrice":{"bid":882,"ask":882.6,"lastTraded":null},"closePrice":{"bid":895.8,"ask":896.4,"lastTraded":null},"highPrice":{"bid":897,"ask":897.6,"lastTraded":null},"lowPrice":{"bid":882,"ask":882.6,"lastTraded":null},"lastTradedVolume":7869},{"snapshotTime":"2022/10/31 18:00:00","openPrice":{"bid":896,"ask":896.6,"lastTraded":null},"closePrice":{"bid":890.3,"ask":891.3,"lastTraded":null},"highPrice":{"bid":898.5,"ask":899.1,"lastTraded":null},"lowPrice":{"bid":890.1,"ask":890.7,"lastTraded":null},"lastTradedVolume":5032},{"snapshotTime":"2022/11/01 00:00:00","openPrice":{"bid":891,"ask":892.5,"lastTraded":null},"closePrice":{"bid":889.6,"ask":890.6,"lastTraded":null},"highPrice":{"bid":892.2,"ask":892.8,"lastTraded":null},"lowPrice":{"bid":887.9,"ask":888.8,"lastTraded":null},"lastTradedVolume":448},{"snapshotTime":"2022/11/01 01:00:00","openPrice":{"bid":884.7,"ask":885.5,"lastTraded":null},"closePrice":{"bid":887.2,"ask":887.8,"lastTraded":null},"highPrice":{"bid":888.6,"ask":889.2,"lastTraded":null},"lowPrice":{"bid":883.6,"ask":884.4,"lastTraded":null},"lastTradedVolume":475},{"snapshotTime":"2022/11/01 02:00:00","openPrice":{"bid":887.3,"ask":887.9,"lastTraded":null},"closePrice":{"bid":887.4,"ask":888,"lastTraded":null},"highPrice":{"bid":888.1,"ask":888.8,"lastTraded":null},"lowPrice":{"bid":885.1,"ask":885.7,"lastTraded":null},"lastTradedVolume":321},{"snapshotTime":"2022/11/01 03:00:00","openPrice":{"bid":887.5,"ask":888.1,"lastTraded":null},"closePrice":{"bid":890.3,"ask":890.9,"lastTraded":null},"highPrice":{"bid":890.3,"ask":890.9,"lastTraded":null},"lowPrice":{"bid":887.1,"ask":887.8,"lastTraded":null},"lastTradedVolume":231},{"snapshotTime":"2022/11/01 04:00:00","openPrice":{"bid":890.2,"ask":890.8,"lastTraded":null},"closePrice":{"bid":892.8,"ask":893.4,"lastTraded":null},"highPrice":{"bid":893.1,"ask":893.7,"lastTraded":null},"lowPrice":{"bid":890.2,"ask":890.8,"lastTraded":null},"lastTradedVolume":196},{"snapshotTime":"2022/11/01 05:00:00","openPrice":{"bid":892.5,"ask":893.5,"lastTraded":null},"closePrice":{"bid":893.1,"ask":893.7,"lastTraded":null},"highPrice":{"bid":893.8,"ask":894.4,"lastTraded":null},"lowPrice":{"bid":890.7,"ask":891.5,"lastTraded":null},"lastTradedVolume":164},{"snapshotTime":"2022/11/01 06:00:00","openPrice":{"bid":892.9,"ask":893.5,"lastTraded":null},"closePrice":{"bid":893,"ask":893.6,"lastTraded":null},"highPrice":{"bid":893.3,"ask":893.9,"lastTraded":null},"lowPrice":{"bid":891.4,"ask":892,"lastTraded":null},"lastTradedVolume":170},{"snapshotTime":"2022/11/01 07:00:00","openPrice":{"bid":892.9,"ask":893.5,"lastTraded":null},"closePrice":{"bid":895.3,"ask":895.9,"lastTraded":null},"highPrice":{"bid":895.8,"ask":896.6,"lastTraded":null},"lowPrice":{"bid":890.6,"ask":891.2,"lastTraded":null},"lastTradedVolume":264},{"snapshotTime":"2022/11/01 08:00:00","openPrice":{"bid":895.4,"ask":896,"lastTraded":null},"closePrice":{"bid":884.2,"ask":884.8,"lastTraded":null},"highPrice":{"bid":896.7,"ask":897.3,"lastTraded":null},"lowPrice":{"bid":884,"ask":884.6,"lastTraded":null},"lastTradedVolume":715},{"snapshotTime":"2022/11/01 09:00:00","openPrice":{"bid":884.1,"ask":884.7,"lastTraded":null},"closePrice":{"bid":886,"ask":886.6,"lastTraded":null},"highPrice":{"bid":886.9,"ask":887.6,"lastTraded":null},"lowPrice":{"bid":880.4,"ask":881,"lastTraded":null},"lastTradedVolume":1140},{"snapshotTime":"2022/11/01 10:00:00","openPrice":{"bid":885.9,"ask":886.5,"lastTraded":null},"closePrice":{"bid":884.5,"ask":885.1,"lastTraded":null},"highPrice":{"bid":888.7,"ask":889.3,"lastTraded":null},"lowPrice":{"bid":884,"ask":884.6,"lastTraded":null},"lastTradedVolume":693},{"snapshotTime":"2022/11/01 11:00:00","openPrice":{"bid":884.4,"ask":885,"lastTraded":null},"closePrice":{"bid":887.5,"ask":888.1,"lastTraded":null},"highPrice":{"bid":890.6,"ask":891.2,"lastTraded":null},"lowPrice":{"bid":882.8,"ask":883.4,"lastTraded":null},"lastTradedVolume":661},{"snapshotTime":"2022/11/01 12:00:00","openPrice":{"bid":887.7,"ask":888.3,"lastTraded":null},"closePrice":{"bid":892.6,"ask":893.2,"lastTraded":null},"highPrice":{"bid":894,"ask":894.6,"lastTraded":null},"lowPrice":{"bid":886.2,"ask":886.8,"lastTraded":null},"lastTradedVolume":1282},{"snapshotTime":"2022/11/01 13:00:00","openPrice":{"bid":893.8,"ask":894.4,"lastTraded":null},"closePrice":{"bid":891.8,"ask":892.4,"lastTraded":null},"highPrice":{"bid":898.3,"ask":898.9,"lastTraded":null},"lowPrice":{"bid":883.4,"ask":884,"lastTraded":null},"lastTradedVolume":7864},{"snapshotTime":"2022/11/01 14:00:00","openPrice":{"bid":892,"ask":892.6,"lastTraded":null},"closePrice":{"bid":890.9,"ask":891.5,"lastTraded":null},"highPrice":{"bid":893.9,"ask":894.5,"lastTraded":null},"lowPrice":{"bid":883.6,"ask":884.2,"lastTraded":null},"lastTradedVolume":8003},{"snapshotTime":"2022/11/01 15:00:00","openPrice":{"bid":891.1,"ask":891.7,"lastTraded":null},"closePrice":{"bid":889.9,"ask":890.5,"lastTraded":null},"highPrice":{"bid":896.8,"ask":897.4,"lastTraded":null},"lowPrice":{"bid":887,"ask":887.6,"lastTraded":null},"lastTradedVolume":7891},{"snapshotTime":"2022/11/01 16:00:00","openPrice":{"bid":889.7,"ask":890.3,"lastTraded":null},"closePrice":{"bid":898.4,"ask":899,"lastTraded":null},"highPrice":{"bid":903.9,"ask":904.5,"lastTraded":null},"lowPrice":{"bid":889.7,"ask":890.3,"lastTraded":null},"lastTradedVolume":7141},{"snapshotTime":"2022/11/01 17:00:00","openPrice":{"bid":898.6,"ask":899.2,"lastTraded":null},"closePrice":{"bid":910.7,"ask":911.3,"lastTraded":null},"highPrice":{"bid":913.3,"ask":913.9,"lastTraded":null},"lowPrice":{"bid":897.2,"ask":897.8,"lastTraded":null},"lastTradedVolume":5669},{"snapshotTime":"2022/11/01 18:00:00","openPrice":{"bid":910.6,"ask":911.2,"lastTraded":null},"closePrice":{"bid":910.3,"ask":910.9,"lastTraded":null},"highPrice":{"bid":915.7,"ask":916.3,"lastTraded":null},"lowPrice":{"bid":909,"ask":909.6,"lastTraded":null},"lastTradedVolume":3900},{"snapshotTime":"2022/11/02 00:00:00","openPrice":{"bid":910.5,"ask":912,"lastTraded":null},"closePrice":{"bid":908.2,"ask":908.8,"lastTraded":null},"highPrice":{"bid":910.8,"ask":912,"lastTraded":null},"lowPrice":{"bid":907.5,"ask":908.1,"lastTraded":null},"lastTradedVolume":225},{"snapshotTime":"2022/11/02 01:00:00","openPrice":{"bid":909.3,"ask":909.9,"lastTraded":null},"closePrice":{"bid":912.7,"ask":913.3,"lastTraded":null},"highPrice":{"bid":912.7,"ask":913.3,"lastTraded":null},"lowPrice":{"bid":906.9,"ask":907.7,"lastTraded":null},"lastTradedVolume":268},{"snapshotTime":"2022/11/02 02:00:00","openPrice":{"bid":912.4,"ask":913.4,"lastTraded":null},"closePrice":{"bid":911.9,"ask":912.5,"lastTraded":null},"highPrice":{"bid":914.1,"ask":914.7,"lastTraded":null},"lowPrice":{"bid":910.1,"ask":910.7,"lastTraded":null},"lastTradedVolume":260},{"snapshotTime":"2022/11/02 03:00:00","openPrice":{"bid":911.5,"ask":912.1,"lastTraded":null},"closePrice":{"bid":911.6,"ask":912.2,"lastTraded":null},"highPrice":{"bid":912.9,"ask":913.5,"lastTraded":null},"lowPrice":{"bid":911.1,"ask":911.7,"lastTraded":null},"lastTradedVolume":134},{"snapshotTime":"2022/11/02 04:00:00","openPrice":{"bid":910.9,"ask":911.9,"lastTraded":null},"closePrice":{"bid":912.2,"ask":912.8,"lastTraded":null},"highPrice":{"bid":913.9,"ask":914.5,"lastTraded":null},"lowPrice":{"bid":910.9,"ask":911.5,"lastTraded":null},"lastTradedVolume":95},{"snapshotTime":"2022/11/02 05:00:00","openPrice":{"bid":912.3,"ask":912.9,"lastTraded":null},"closePrice":{"bid":907.4,"ask":908,"lastTraded":null},"highPrice":{"bid":912.7,"ask":913.3,"lastTraded":null},"lowPrice":{"bid":907.3,"ask":907.9,"lastTraded":null},"lastTradedVolume":211},{"snapshotTime":"2022/11/02 06:00:00","openPrice":{"bid":907.3,"ask":907.9,"lastTraded":null},"closePrice":{"bid":906.1,"ask":906.7,"lastTraded":null},"highPrice":{"bid":908.9,"ask":909.6,"lastTraded":null},"lowPrice":{"bid":905.6,"ask":906.2,"lastTraded":null},"lastTradedVolume":601},{"snapshotTime":"2022/11/02 08:00:00","openPrice":{"bid":907.1,"ask":907.7,"lastTraded":null},"closePrice":{"bid":905.3,"ask":905.9,"lastTraded":null},"highPrice":{"bid":910.7,"ask":911.3,"lastTraded":null},"lowPrice":{"bid":904.3,"ask":904.9,"lastTraded":null},"lastTradedVolume":462},{"snapshotTime":"2022/11/02 09:00:00","openPrice":{"bid":905,"ask":905.6,"lastTraded":null},"closePrice":{"bid":907.8,"ask":908.8,"lastTraded":null},"highPrice":{"bid":909.6,"ask":910.2,"lastTraded":null},"lowPrice":{"bid":904.8,"ask":905.4,"lastTraded":null},"lastTradedVolume":491},{"snapshotTime":"2022/11/02 10:00:00","openPrice":{"bid":908,"ask":908.6,"lastTraded":null},"closePrice":{"bid":861,"ask":862,"lastTraded":null},"highPrice":{"bid":908,"ask":908.8,"lastTraded":null},"lowPrice":{"bid":856.6,"ask":857.6,"lastTraded":null},"lastTradedVolume":12011},{"snapshotTime":"2022/11/02 11:00:00","openPrice":{"bid":861.1,"ask":862.1,"lastTraded":null},"closePrice":{"bid":866.4,"ask":867,"lastTraded":null},"highPrice":{"bid":867.8,"ask":868.5,"lastTraded":null},"lowPrice":{"bid":860,"ask":860.7,"lastTraded":null},"lastTradedVolume":3403},{"snapshotTime":"2022/11/02 12:00:00","openPrice":{"bid":865.8,"ask":866.4,"lastTraded":null},"closePrice":{"bid":862.3,"ask":862.9,"lastTraded":null},"highPrice":{"bid":867.8,"ask":868.4,"lastTraded":null},"lowPrice":{"bid":859.8,"ask":860.6,"lastTraded":null},"lastTradedVolume":3659},{"snapshotTime":"2022/11/02 13:00:00","openPrice":{"bid":861.9,"ask":862.5,"lastTraded":null},"closePrice":{"bid":858.2,"ask":858.8,"lastTraded":null},"highPrice":{"bid":867.6,"ask":868.2,"lastTraded":null},"lowPrice":{"bid":855,"ask":855.6,"lastTraded":null},"lastTradedVolume":7389},{"snapshotTime":"2022/11/02 14:00:00","openPrice":{"bid":858.1,"ask":858.7,"lastTraded":null},"closePrice":{"bid":861.2,"ask":861.8,"lastTraded":null},"highPrice":{"bid":861.2,"ask":861.8,"lastTraded":null},"lowPrice":{"bid":854.4,"ask":855,"lastTraded":null},"lastTradedVolume":7407},{"snapshotTime":"2022/11/02 15:00:00","openPrice":{"bid":861.1,"ask":861.7,"lastTraded":null},"closePrice":{"bid":855.3,"ask":855.9,"lastTraded":null},"highPrice":{"bid":861.2,"ask":861.8,"lastTraded":null},"lowPrice":{"bid":853.8,"ask":854.4,"lastTraded":null},"lastTradedVolume":6485},{"snapshotTime":"2022/11/02 16:00:00","openPrice":{"bid":855.4,"ask":856,"lastTraded":null},"closePrice":{"bid":857.7,"ask":858.3,"lastTraded":null},"highPrice":{"bid":859.4,"ask":860,"lastTraded":null},"lowPrice":{"bid":851.4,"ask":852,"lastTraded":null},"lastTradedVolume":4793},{"snapshotTime":"2022/11/02 17:00:00","openPrice":{"bid":857.8,"ask":858.4,"lastTraded":null},"closePrice":{"bid":856.5,"ask":857.1,"lastTraded":null},"highPrice":{"bid":860.7,"ask":861.3,"lastTraded":null},"lowPrice":{"bid":854.8,"ask":855.4,"lastTraded":null},"lastTradedVolume":5064},{"snapshotTime":"2022/11/02 18:00:00","openPrice":{"bid":856.4,"ask":857,"lastTraded":null},"closePrice":{"bid":858.6,"ask":859.2,"lastTraded":null},"highPrice":{"bid":860.6,"ask":861.2,"lastTraded":null},"lowPrice":{"bid":855.3,"ask":855.9,"lastTraded":null},"lastTradedVolume":4989},{"snapshotTime":"2022/11/03 00:00:00","openPrice":{"bid":860.2,"ask":860.8,"lastTraded":null},"closePrice":{"bid":855.3,"ask":856.3,"lastTraded":null},"highPrice":{"bid":860.6,"ask":861.3,"lastTraded":null},"lowPrice":{"bid":855.1,"ask":855.7,"lastTraded":null},"lastTradedVolume":262},{"snapshotTime":"2022/11/03 01:00:00","openPrice":{"bid":854.4,"ask":855,"lastTraded":null},"closePrice":{"bid":854.3,"ask":854.9,"lastTraded":null},"highPrice":{"bid":857.7,"ask":858.5,"lastTraded":null},"lowPrice":{"bid":852.6,"ask":853.2,"lastTraded":null},"lastTradedVolume":320},{"snapshotTime":"2022/11/03 02:00:00","openPrice":{"bid":854.2,"ask":854.8,"lastTraded":null},"closePrice":{"bid":852.7,"ask":853.3,"lastTraded":null},"highPrice":{"bid":854.5,"ask":855.3,"lastTraded":null},"lowPrice":{"bid":852,"ask":852.6,"lastTraded":null},"lastTradedVolume":207},{"snapshotTime":"2022/11/03 03:00:00","openPrice":{"bid":852.6,"ask":853.2,"lastTraded":null},"closePrice":{"bid":852.2,"ask":852.8,"lastTraded":null},"highPrice":{"bid":853.9,"ask":854.5,"lastTraded":null},"lowPrice":{"bid":851.4,"ask":852,"lastTraded":null},"lastTradedVolume":349},{"snapshotTime":"2022/11/03 04:00:00","openPrice":{"bid":852.1,"ask":852.7,"lastTraded":null},"closePrice":{"bid":851.3,"ask":852.3,"lastTraded":null},"highPrice":{"bid":852.7,"ask":853.5,"lastTraded":null},"lowPrice":{"bid":851.1,"ask":851.7,"lastTraded":null},"lastTradedVolume":138},{"snapshotTime":"2022/11/03 05:00:00","openPrice":{"bid":851.4,"ask":852,"lastTraded":null},"closePrice":{"bid":851.7,"ask":852.3,"lastTraded":null},"highPrice":{"bid":852.4,"ask":853,"lastTraded":null},"lowPrice":{"bid":850.3,"ask":851,"lastTraded":null},"lastTradedVolume":103},{"snapshotTime":"2022/11/03 06:00:00","openPrice":{"bid":851.6,"ask":852.2,"lastTraded":null},"closePrice":{"bid":849.8,"ask":850.8,"lastTraded":null},"highPrice":{"bid":851.6,"ask":852.2,"lastTraded":null},"lowPrice":{"bid":847.9,"ask":848.7,"lastTraded":null},"lastTradedVolume":362},{"snapshotTime":"2022/11/03 07:00:00","openPrice":{"bid":849.9,"ask":850.5,"lastTraded":null},"closePrice":{"bid":849.3,"ask":849.9,"lastTraded":null},"highPrice":{"bid":850,"ask":850.8,"lastTraded":null},"lowPrice":{"bid":845.9,"ask":846.5,"lastTraded":null},"lastTradedVolume":518},{"snapshotTime":"2022/11/03 08:00:00","openPrice":{"bid":849.2,"ask":849.8,"lastTraded":null},"closePrice":{"bid":846.6,"ask":847.2,"lastTraded":null},"highPrice":{"bid":849.3,"ask":850,"lastTraded":null},"lowPrice":{"bid":844.9,"ask":845.5,"lastTraded":null},"lastTradedVolume":1651},{"snapshotTime":"2022/11/03 09:00:00","openPrice":{"bid":846.4,"ask":847,"lastTraded":null},"closePrice":{"bid":845.3,"ask":845.9,"lastTraded":null},"highPrice":{"bid":847.4,"ask":848.1,"lastTraded":null},"lowPrice":{"bid":843.3,"ask":844,"lastTraded":null},"lastTradedVolume":655},{"snapshotTime":"2022/11/03 10:00:00","openPrice":{"bid":845.1,"ask":846.1,"lastTraded":null},"closePrice":{"bid":847.2,"ask":847.8,"lastTraded":null},"highPrice":{"bid":848.1,"ask":848.7,"lastTraded":null},"lowPrice":{"bid":844.4,"ask":845,"lastTraded":null},"lastTradedVolume":885},{"snapshotTime":"2022/11/03 11:00:00","openPrice":{"bid":847.3,"ask":847.9,"lastTraded":null},"closePrice":{"bid":845.5,"ask":846.1,"lastTraded":null},"highPrice":{"bid":847.9,"ask":848.5,"lastTraded":null},"lowPrice":{"bid":844.4,"ask":845,"lastTraded":null},"lastTradedVolume":621},{"snapshotTime":"2022/11/03 12:00:00","openPrice":{"bid":845.6,"ask":846.2,"lastTraded":null},"closePrice":{"bid":843.5,"ask":844.1,"lastTraded":null},"highPrice":{"bid":845.9,"ask":846.5,"lastTraded":null},"lowPrice":{"bid":842.2,"ask":842.8,"lastTraded":null},"lastTradedVolume":616},{"snapshotTime":"2022/11/03 13:00:00","openPrice":{"bid":842.5,"ask":843.1,"lastTraded":null},"closePrice":{"bid":856.6,"ask":857.2,"lastTraded":null},"highPrice":{"bid":858.7,"ask":859.3,"lastTraded":null},"lowPrice":{"bid":842,"ask":842.6,"lastTraded":null},"lastTradedVolume":5512},{"snapshotTime":"2022/11/03 14:00:00","openPrice":{"bid":856.8,"ask":857.4,"lastTraded":null},"closePrice":{"bid":861.1,"ask":861.7,"lastTraded":null},"highPrice":{"bid":862.8,"ask":863.4,"lastTraded":null},"lowPrice":{"bid":855.1,"ask":855.7,"lastTraded":null},"lastTradedVolume":5945},{"snapshotTime":"2022/11/03 17:00:00","openPrice":{"bid":857.4,"ask":858,"lastTraded":null},"closePrice":{"bid":856.2,"ask":856.8,"lastTraded":null},"highPrice":{"bid":858.9,"ask":859.5,"lastTraded":null},"lowPrice":{"bid":854.5,"ask":855.1,"lastTraded":null},"lastTradedVolume":2622},{"snapshotTime":"2022/11/03 18:00:00","openPrice":{"bid":856.4,"ask":857,"lastTraded":null},"closePrice":{"bid":853.8,"ask":854.4,"lastTraded":null},"highPrice":{"bid":856.6,"ask":857.2,"lastTraded":null},"lowPrice":{"bid":852.8,"ask":853.4,"lastTraded":null},"lastTradedVolume":3722},{"snapshotTime":"2022/11/04 00:00:00","openPrice":{"bid":856.2,"ask":856.8,"lastTraded":null},"closePrice":{"bid":857,"ask":857.6,"lastTraded":null},"highPrice":{"bid":858.4,"ask":859,"lastTraded":null},"lowPrice":{"bid":856.2,"ask":856.8,"lastTraded":null},"lastTradedVolume":169},{"snapshotTime":"2022/11/04 01:00:00","openPrice":{"bid":855.9,"ask":856.5,"lastTraded":null},"closePrice":{"bid":858.1,"ask":858.7,"lastTraded":null},"highPrice":{"bid":858.6,"ask":859.2,"lastTraded":null},"lowPrice":{"bid":852.7,"ask":853.3,"lastTraded":null},"lastTradedVolume":379},{"snapshotTime":"2022/11/04 02:00:00","openPrice":{"bid":857.9,"ask":858.5,"lastTraded":null},"closePrice":{"bid":860.6,"ask":861.2,"lastTraded":null},"highPrice":{"bid":861.3,"ask":861.9,"lastTraded":null},"lowPrice":{"bid":856.9,"ask":857.6,"lastTraded":null},"lastTradedVolume":149}]